libnuml/__init__.py
libnuml/_libnuml.cp312-win32.pyd
python_libnuml-1.1.7.dist-info/licenses/LICENSE.txt
python_libnuml-1.1.7.dist-info/METADATA
python_libnuml-1.1.7.dist-info/WHEEL
python_libnuml-1.1.7.dist-info/top_level.txt
python_libnuml-1.1.7.dist-info/RECORD
